pyforms/__init__.py
pyforms/basewidget.py
pyforms/controls.py
pyforms/dialogs.py
pyforms/settings.py
pyforms_web/__init__.py
pyforms_web/allcontrols.py
pyforms_web/appmanager.py
pyforms_web/basewidget.py
pyforms_web/organizers.py
pyforms_web/settings.py
pyforms_web/utils.py
pyforms_web/controls/__init__.py
pyforms_web/controls/control_autocomplete.py
pyforms_web/controls/control_barschart.py
pyforms_web/controls/control_base.py
pyforms_web/controls/control_boundingslider.py
pyforms_web/controls/control_breadcrumb.py
pyforms_web/controls/control_button.py
pyforms_web/controls/control_calendar.py
pyforms_web/controls/control_checkbox.py
pyforms_web/controls/control_checkboxlist.py
pyforms_web/controls/control_checkboxlistquery.py
pyforms_web/controls/control_codemirror.py
pyforms_web/controls/control_combo.py
pyforms_web/controls/control_date.py
pyforms_web/controls/control_datetime.py
pyforms_web/controls/control_decimal.py
pyforms_web/controls/control_dir.py
pyforms_web/controls/control_email.py
pyforms_web/controls/control_emptywidget.py
pyforms_web/controls/control_feed.py
pyforms_web/controls/control_file.py
pyforms_web/controls/control_fileupload.py
pyforms_web/controls/control_float.py
pyforms_web/controls/control_html.py
pyforms_web/controls/control_image.py
pyforms_web/controls/control_img.py
pyforms_web/controls/control_integer.py
pyforms_web/controls/control_itemslist.py
pyforms_web/controls/control_label.py
pyforms_web/controls/control_linechart.py
pyforms_web/controls/control_list.py
pyforms_web/controls/control_menu.py
pyforms_web/controls/control_multiplechecks.py
pyforms_web/controls/control_multipleselection.py
pyforms_web/controls/control_multipleselectionquery.py
pyforms_web/controls/control_multipleupload.py
pyforms_web/controls/control_organogram.py
pyforms_web/controls/control_password.py
pyforms_web/controls/control_piechart.py
pyforms_web/controls/control_player.py
pyforms_web/controls/control_playerjs.py
PyForms_Web-4.2.0.dist-info/METADATA
PyForms_Web-4.2.0.dist-info/WHEEL
PyForms_Web-4.2.0.dist-info/top_level.txt
PyForms_Web-4.2.0.dist-info/RECORD
